[
  {
    "name": "Ankit Enterprises",
    "contact_person": "Ankit Jolly",
    "email": "ajolly@serviceats.com",
    "email_cc": "info@zorrofin.com",
    "phone": "0129664455",
    "mobile": "9898989898",
    "whatsapp_number": "9898989898",
    "company_name": "SARAI, Haryana",
    "additional_address_lines": [],
    "customer_id": "209",
    "biller_id": "a6ca7e76-34b7-40db-85e4-481ccc5f662f",
    "gstin": "",
    "gst_registration_type": "",
    "gst_state": "",
    "bank_details": [
      {
        "bank_name": "",
        "account_number": "",
        "ifsc_code": "",
        "branch": ""
      }
    ],
    "opening_balance": -7000,
    "current_balance": -159724.4,
    "current_balance_at": "2025-12-22 16:32:02",
    "invoice_details": []
  },
  {
    "name": "Company   Test 001",
    "contact_person": "",
    "email": "",
    "email_cc": "",
    "phone": "",
    "mobile": "",
    "whatsapp_number": "",
    "company_name": "",
    "additional_address_lines": [],
    "customer_id": "217",
    "biller_id": "a6ca7e76-34b7-40db-85e4-481ccc5f662f",
    "gstin": "",
    "gst_registration_type": "",
    "gst_state": "",
    "bank_details": [
      {
        "bank_name": "",
        "account_number": "",
        "ifsc_code": "",
        "branch": ""
      }
    ],
    "opening_balance": 0,
    "current_balance": 0,
    "current_balance_at": "2025-12-22 16:32:02",
    "invoice_details": []
  },
  {
    "name": "Company Test 002",
    "contact_person": "",
    "email": "",
    "email_cc": "",
    "phone": "",
    "mobile": "",
    "whatsapp_number": "",
    "company_name": "",
    "additional_address_lines": [],
    "customer_id": "218",
    "biller_id": "a6ca7e76-34b7-40db-85e4-481ccc5f662f",
    "gstin": "",
    "gst_registration_type": "",
    "gst_state": "",
    "bank_details": [
      {
        "bank_name": "",
        "account_number": "",
        "ifsc_code": "",
        "branch": ""
      }
    ],
    "opening_balance": -3000,
    "current_balance": -3000,
    "current_balance_at": "2025-12-22 16:32:02",
    "invoice_details": []
  },
  {
    "name": "Company Test 003",
    "contact_person": "",
    "email": "",
    "email_cc": "",
    "phone": "",
    "mobile": "",
    "whatsapp_number": "",
    "company_name": "",
    "additional_address_lines": [],
    "customer_id": "220",
    "biller_id": "a6ca7e76-34b7-40db-85e4-481ccc5f662f",
    "gstin": "",
    "gst_registration_type": "",
    "gst_state": "",
    "bank_details": [
      {
        "bank_name": "",
        "account_number": "",
        "ifsc_code": "",
        "branch": ""
      }
    ],
    "opening_balance": 0,
    "current_balance": 0,
    "current_balance_at": "2025-12-22 16:32:02",
    "invoice_details": []
  },
  {
    "name": "Customer Test 004",
    "contact_person": "Koushik Mandal",
    "email": "koushikmandal@mobotics.in",
    "email_cc": "",
    "phone": "8848735",
    "mobile": "64645656",
    "whatsapp_number": "64645656",
    "company_name": "Gosaba, South 24 Pgs, West Bengal",
    "additional_address_lines": [],
    "customer_id": "221",
    "biller_id": "a6ca7e76-34b7-40db-85e4-481ccc5f662f",
    "gstin": "",
    "gst_registration_type": "",
    "gst_state": "",
    "bank_details": [
      {
        "bank_name": "",
        "account_number": "",
        "ifsc_code": "",
        "branch": ""
      }
    ],
    "opening_balance": -5000,
    "current_balance": -5000,
    "current_balance_at": "2025-12-22 16:32:02",
    "invoice_details": []
  }
]